LICENSE
MANIFEST.in
NOTICE
README.md
pyproject.toml
requirements-dev.txt
requirements.txt
setup.py
vwo/__init__.py
vwo/vwo.py
vwo/api/__init__.py
vwo/api/activate.py
vwo/api/flush_events.py
vwo/api/get_and_update_settings_file.py
vwo/api/get_feature_variable_value.py
vwo/api/get_variation_name.py
vwo/api/is_feature_enabled.py
vwo/api/launch.py
vwo/api/push.py
vwo/api/set_opt_out.py
vwo/api/track.py
vwo/constants/__init__.py
vwo/constants/constants.py
vwo/core/__init__.py
vwo/core/bucketer.py
vwo/core/variation_decider.py
vwo/enums/__init__.py
vwo/enums/file_name_enum.py
vwo/enums/hooks_enum.py
vwo/enums/log_level_enum.py
vwo/enums/log_message_enum.py
vwo/enums/segments/__init__.py
vwo/enums/segments/operand_types.py
vwo/enums/segments/operand_value_boolean_types.py
vwo/enums/segments/operand_value_types.py
vwo/enums/segments/operand_value_types_name.py
vwo/enums/segments/operator_types.py
vwo/enums/segments/result_status.py
vwo/event/__init__.py
vwo/event/event_dispatcher.py
vwo/helpers/__init__.py
vwo/helpers/campaign_util.py
vwo/helpers/custom_dimensions_util.py
vwo/helpers/feature_util.py
vwo/helpers/generic_util.py
vwo/helpers/impression_util.py
vwo/helpers/segment_utils.py
vwo/helpers/settings_file_util.py
vwo/helpers/uuid_util.py
vwo/helpers/validate_util.py
vwo/http/__init__.py
vwo/http/connection.py
vwo/logger/VWOLogger.py
vwo/logger/__init__.py
vwo/schemas/__init__.py
vwo/schemas/campaign_group_schema.py
vwo/schemas/campaign_schema.py
vwo/schemas/empty_object_schema.py
vwo/schemas/goal_schema.py
vwo/schemas/group_schema.py
vwo/schemas/settings_file_schema.py
vwo/schemas/variable_schema.py
vwo/schemas/variation_schema.py
vwo/services/__init__.py
vwo/services/hooks_manager.py
vwo/services/settings_file_manager.py
vwo/services/url_manager.py
vwo/services/usage_stats_manager.py
vwo/services/segmentor/__init__.py
vwo/services/segmentor/operand_evaluator.py
vwo/services/segmentor/segment_evaluator.py
vwo/storage/__init__.py
vwo/storage/redis.py
vwo_python_sdk.egg-info/PKG-INFO
vwo_python_sdk.egg-info/SOURCES.txt
vwo_python_sdk.egg-info/dependency_links.txt
vwo_python_sdk.egg-info/requires.txt
vwo_python_sdk.egg-info/top_level.txt