Metadata-Version: 2.1
Name: vwo-python-sdk
Version: 1.68.2
Summary: Python SDK for VWO server-side A/B Testing
Home-page: https://github.com/wingify/vwo-python-sdk
Author: VWO
Author-email: dev@wingify.com
License: Apache License 2.0
Classifier: Development Status :: 5 - Production/Stable
Classifier: Environment :: Web Environment
Classifier: Intended Audience :: Developers
Classifier: License :: OSI Approved :: Apache Software License
Classifier: Operating System :: OS Independent
Classifier: Programming Language :: Python
Classifier: Programming Language :: Python :: 2.7
Classifier: Programming Language :: Python :: 3.4
Classifier: Programming Language :: Python :: 3.5
Classifier: Programming Language :: Python :: 3.6
Classifier: Programming Language :: Python :: 3.7
License-File: LICENSE
License-File: NOTICE
